ept/__init__.py
ept/_nbdev.py
ept/algorithms.py
ept/crossover.py
ept/mutation.py
ept/parameter.py
ept/sample_cases.py
ept/tuner.py
ept/utils.py
eptune/__init__.py
eptune/_nbdev.py
eptune/algorithms.py
eptune/crossover.py
eptune/example.py
eptune/mutation.py
eptune/parameter.py
eptune/quick.py
eptune/sample_cases.py
eptune/sklearn.py
eptune/utils.py
eptune-0.1.7.dist-info/LICENSE
eptune-0.1.7.dist-info/METADATA
eptune-0.1.7.dist-info/WHEEL
eptune-0.1.7.dist-info/entry_points.txt
eptune-0.1.7.dist-info/top_level.txt
eptune-0.1.7.dist-info/RECORD
