Metadata-Version: 2.1
Name: eptune
Version: 0.1.7
Summary: Evolutionary parameter tuning
Home-page: https://github.com/wanglongqi/eptune/tree/master/
Author: Longqi
Author-email: iqgnol@gmail.com
License: GNU Lesser General Public License v3.0
Keywords: genetic programing
Platform: UNKNOWN
Classifier: Development Status :: 5 - Production/Stable
Classifier: Intended Audience :: Developers
Classifier: License :: OSI Approved :: GNU Lesser General Public License v3 or later (LGPLv3+)
Classifier: Natural Language :: English
Classifier: Programming Language :: Python :: 3.6
Classifier: Programming Language :: Python :: 3.7
Classifier: Programming Language :: Python :: 3.8
Requires-Python: >=3.6
Requires-Dist: deap
Requires-Dist: scikit-learn
Requires-Dist: matplotlib
